desmondtools/__init__.py
desmondtools/cli.py
desmondtools/desmond-md.cfg
desmondtools/desmond-md.msj
desmondtools/desmond-metad.cfg
desmondtools/desmond-metad.msj
desmondtools/desmond-min.cfg
desmondtools/desmond-min.msj
desmondtools/desmond-rmsx-analysis.eaf
desmondtools/desmond-setup.msj
desmondtools/event.py
desmondtools/multisim.py
desmondtools/cli/__init__.py
desmondtools/cli/batch_desmond_cms2dcd.py
desmondtools/cli/batch_desmond_md.py
desmondtools/cli/batch_desmond_mdinfo.py
desmondtools/cli/batch_desmond_metad.py
desmondtools/cli/batch_desmond_min.py
desmondtools/cli/batch_desmond_mmgbsa.py
desmondtools/cli/batch_desmond_pli.py
desmondtools/cli/batch_desmond_report.py
desmondtools/cli/batch_desmond_rmsx.py
desmondtools/cli/batch_desmond_setup.py
desmondtools/cli/schrodinger_run.py
desmondtools/script/batch-cmsinfo.py
desmondtools/script/batch-desmond-cmsinfo.py
desmondtools/script/batch-desmond-dihedral.py
desmondtools/script/batch-desmond-distance.py
desmondtools/script/batch-desmond-ligrmsd.py
desmondtools/script/batch-desmond-maeinfo.py
desmondtools/script/batch-desmond-mmgbsa.py
desmondtools/script/batch-desmond-report.py
desmondtools/script/batch-desmond-rg.py
desmondtools/script/batch-desmond-rmsx.py
desmondtools/script/batch-maeinfo.py
desmondtools-1.1.1.dist-info/licenses/LICENSE
desmondtools-1.1.1.dist-info/METADATA
desmondtools-1.1.1.dist-info/WHEEL
desmondtools-1.1.1.dist-info/entry_points.txt
desmondtools-1.1.1.dist-info/top_level.txt
desmondtools-1.1.1.dist-info/RECORD
