Metadata-Version: 2.4
Name: desmondtools
Version: 1.1.1
Summary: Tools for Desmond molecular dynamics
Author-email: Sung-Hun Bae <sunghun.bae@gmail.com>
Maintainer-email: Sung-Hun Bae <sunghun.bae@gmail.com>
License-Expression: MIT
Project-URL: Homepage, https://github.com/sunghunbae/desmondtools
Project-URL: Repository, https://github.com/sunghunbae/desmondtools.git
Project-URL: Issues, https://github.com/sunghunbae/desmondtools/issues
Project-URL: Changelog, https://github.com/sunghunbae/desmondtools/blob/master/CHANGELOG.md
Project-URL: Documentation, https://sunghunbae.github.io/desmondtools/
Keywords: Desmond,Multisim,Molecular Dynamics
Classifier: Development Status :: 3 - Alpha
Classifier: Intended Audience :: Developers
Classifier: Programming Language :: Python :: 3
Classifier: Operating System :: OS Independent
Requires-Python: >=3.11
License-File: LICENSE
Requires-Dist: pyparsing>=3.0
Requires-Dist: dotmap>=1.3
Requires-Dist: pandas
Requires-Dist: numpy
Requires-Dist: pytest
Dynamic: license-file
